cityImage/__init__.py
cityImage/angles.py
cityImage/barriers.py
cityImage/centrality.py
cityImage/clean.py
cityImage/colors.py
cityImage/graph.py
cityImage/land_use.py
cityImage/landmarks.py
cityImage/load.py
cityImage/plot.py
cityImage/regions.py
cityImage/utilities.py
tests/__init__.py
tests/test_cityImage.py
cityImage-1.10.dist-info/LICENSE.txt
cityImage-1.10.dist-info/METADATA
cityImage-1.10.dist-info/WHEEL
cityImage-1.10.dist-info/top_level.txt
cityImage-1.10.dist-info/RECORD
