Metadata-Version: 2.1
Name: cityImage
Version: 1.10
Summary: A package for studying urban form and obtaining the computational Image of the City
Author: Gabriele Filomena
Author-email: gabriele.filomena@liverpool.ac.uk
Keywords: urban Form Analysis,Computational Image of the City,Kevin Lynch,cognitive maps
License-File: LICENSE.txt
Requires-Dist: osmnx >=1.9.1
Requires-Dist: python-louvain >=0.16
Requires-Dist: pyvista >=0.37
Requires-Dist: mapclassify >=2.5.0
